LICENSE.txt
README.rst
flask_arango_orm/__init__.py
flask_arango_orm/arango.py
flask_arango_orm-0.2.0.dist-info/LICENSE.txt
flask_arango_orm-0.2.0.dist-info/METADATA
flask_arango_orm-0.2.0.dist-info/WHEEL
flask_arango_orm-0.2.0.dist-info/RECORD
