Metadata-Version: 2.1
Name: Flask-arango-orm
Version: 0.2.0
Summary: Flask connector for ArangoDB using arango-orm
Home-page: https://github.com/QuaererePlatform/Flask-arango-orm
License: LGPL-3.0-or-later
Author: ravenoak
Author-email: ravenoak@virtualxistenz.com
Requires-Python: >=3.8,<4.0
Classifier: Development Status :: 2 - Pre-Alpha
Classifier: Environment :: Plugins
Classifier: Environment :: Web Environment
Classifier: Framework :: Flask
Classifier: Intended Audience :: Developers
Classifier: License :: OSI Approved :: GNU Lesser General Public License v3 or later (LGPLv3+)
Classifier: Operating System :: OS Independent
Classifier: Programming Language :: Python :: 3
Classifier: Programming Language :: Python :: 3.8
Classifier: Programming Language :: Python :: 3.9
Classifier: Programming Language :: Python :: 3.10
Classifier: Programming Language :: Python :: 3.11
Classifier: Programming Language :: Python :: 3 :: Only
Classifier: Topic :: Database
Classifier: Topic :: Internet :: WWW/HTTP :: WSGI
Classifier: Topic :: Software Development :: Libraries :: Python Modules
Requires-Dist: arango-orm (>=0.7.2)
Requires-Dist: flask (>=2.0.0)
Requires-Dist: python-arango (>=7)
Project-URL: Documentation, http://flask-arango-orm.readthedocs.io/
Project-URL: Repository, https://github.com/QuaererePlatform/Flask-arango-orm
